analysis2template/__init__.py
analysis2template/__main__.py
analysis2template-0.0.1.dist-info/LICENSE
analysis2template-0.0.1.dist-info/METADATA
analysis2template-0.0.1.dist-info/WHEEL
analysis2template-0.0.1.dist-info/entry_points.txt
analysis2template-0.0.1.dist-info/top_level.txt
analysis2template-0.0.1.dist-info/RECORD
