Metadata-Version: 2.1
Name: analysis2template
Version: 0.0.1
Summary: Converts and existing Amazon QuickSight analysis to a template in Terraform format.
Home-page: https://github.com/QuiNovas/analysis2template
License: Apache 2.0
Classifier: License :: Other/Proprietary License
Classifier: Programming Language :: Python :: 3
Classifier: Programming Language :: Python :: 3.9
Requires-Python: >=3.7
License-File: LICENSE
Requires-Dist: argh >=0.27
Requires-Dist: boto3 <1.33.5,>=1.28
Requires-Dist: termcolor ==2.3.0
